abs_repository_core/__init__.py
abs_repository_core/models/__init__.py
abs_repository_core/models/base_model.py
abs_repository_core/repository/__init__.py
abs_repository_core/repository/base_repository.py
abs_repository_core/schemas/__init__.py
abs_repository_core/schemas/base_schema.py
abs_repository_core/services/__init__.py
abs_repository_core/services/base_service.py
abs_repository_core/utils/__init__.py
abs_repository_core/utils/get_field.py
abs_repository_core/utils/schema.py
abs_repository_core-0.3.1.dist-info/METADATA
abs_repository_core-0.3.1.dist-info/WHEEL
abs_repository_core-0.3.1.dist-info/RECORD
