Metadata-Version: 2.3
Name: abs-repository-core
Version: 0.3.1
Summary: Shared base repository and service utilities for SQLAlchemy-backed FastAPI apps.
License: MIT
Author: AutoBridgeSystems
Author-email: info@autobridgesystems.com
Requires-Python: >=3.11
Classifier: License :: OSI Approved :: MIT License
Classifier: Programming Language :: Python :: 3
Classifier: Programming Language :: Python :: 3.11
Classifier: Programming Language :: Python :: 3.12
Classifier: Programming Language :: Python :: 3.13
Requires-Dist: abs-exception-core (>=0.2.1,<0.3.0)
Requires-Dist: fastapi[standard] (>=0.115.2,<0.116.0)
Requires-Dist: sqlalchemy (>=2.0.40,<3.0.0)
